muffin_session/__init__.py
muffin_session/py.typed
muffin_session-2.6.0.dist-info/METADATA
muffin_session-2.6.0.dist-info/WHEEL
muffin_session-2.6.0.dist-info/RECORD
