Metadata-Version: 2.3
Name: muffin-session
Version: 2.6.0
Summary: Signed Cookie-Based HTTP sessions for the Muffin framework
License: MIT
Keywords: asyncio,trio,asgi,muffin,web,cookie,sessions,session
Author: Kirill Klenov
Author-email: horneds@gmail.com
Requires-Python: >=3.10,<4.0
Classifier: Development Status :: 5 - Production/Stable
Classifier: Framework :: AsyncIO
Classifier: Framework :: Trio
Classifier: Intended Audience :: Developers
Classifier: License :: OSI Approved :: MIT License
Classifier: Programming Language :: Python
Classifier: Programming Language :: Python :: 3
Classifier: Programming Language :: Python :: 3.10
Classifier: Programming Language :: Python :: 3.11
Classifier: Programming Language :: Python :: 3.12
Classifier: Programming Language :: Python :: 3.13
Classifier: Topic :: Internet :: WWW/HTTP
Provides-Extra: fernet
Provides-Extra: jwt
Requires-Dist: asgi-sessions[jwt] (>=1,<2)
Requires-Dist: cryptography ; extra == "fernet"
Requires-Dist: muffin
Requires-Dist: pyjwt ; extra == "jwt"
Project-URL: Homepage, https://github.com/klen/muffin-session
Project-URL: Repository, https://github.com/klen/muffin-session
